sudoh/__init__.py
sudoh/cli.py
sudoh-0.1.0.dist-info/METADATA
sudoh-0.1.0.dist-info/WHEEL
sudoh-0.1.0.dist-info/entry_points.txt
sudoh-0.1.0.dist-info/top_level.txt
sudoh-0.1.0.dist-info/RECORD
